pytest_mpiexec/__init__.py
pytest_mpiexec/pytest_plugin.py
pytest_mpiexec-0.0.1a3.dist-info/METADATA
pytest_mpiexec-0.0.1a3.dist-info/WHEEL
pytest_mpiexec-0.0.1a3.dist-info/entry_points.txt
pytest_mpiexec-0.0.1a3.dist-info/licenses/LICENSE
pytest_mpiexec-0.0.1a3.dist-info/RECORD
