Metadata-Version: 2.3
Name: pytest-mpiexec
Version: 0.0.1a3
Summary: pytest plugin for running individual tests with mpiexec
Project-URL: Documentation, https://github.com/minrk/pytest-mpiexec#readme
Project-URL: Issues, https://github.com/minrk/pytest-mpiexec/issues
Project-URL: Source, https://github.com/minrk/pytest-mpiexec
Author-email: Min RK <benjaminrk@gmail.com>
License: MIT License
License-File: LICENSE
Keywords: mpi,pytest
Classifier: Development Status :: 3 - Alpha
Classifier: Framework :: Pytest
Classifier: License :: OSI Approved :: MIT License
Classifier: Operating System :: OS Independent
Classifier: Programming Language :: Python :: 3
Requires-Python: >=3.7
Requires-Dist: mpi4py
Requires-Dist: pytest
Requires-Dist: pytest-reportlog
